[
  {
      "id": 1,
      "Country": "Afghanistan"
  },
  {
      "id": 2,
      "Country": "Albania"
  },
  {
      "id": 3,
      "Country": "Algeria"
  },
  {
      "id": 4,
      "Country": "Argentina"
  },
  {
      "id": 5,
      "Country": "Australia"
  },
  {
      "id": 6,
      "Country": "Bangladesh"
  },
  {
      "id": 7,
      "Country": "Belgium"
  },
  {
      "id": 8,
      "Country": "Brazil"
  },
  {
      "id": 9,
      "Country": "Bulgaria"
  },

  {
      "id": 10,
      "Country": "Canada"
  },
  {
      "id": 11,
      "Country": "China"
  },
  {
      "id": 12,
      "Country": "Columbia"
  },
  {
      "id": 13,
      "Country": "Denmark"
  },
  {
      "id": 14,
      "Country": "Ecuador"
  },
  {
      "id": 15,
      "Country": "Egypt"
  },
  {
      "id": 16,
      "Country": "France"
  },
  {
      "id": 17,
      "Country": "Germany"
  },
  {
      "id": 18,
      "Country": "India"
  },
  {
      "id": 19,
      "Country": "Iran"
  },
  {
      "id": 20,
      "Country": "Italy"
  },
  {
      "id": 21,
      "Country": "Japan"
  },
  {
      "id": 22,
      "Country": "Lebanon"
  },
  {
      "id": 23,
      "Country": "Mexico"
  },
  {
      "id": 24,
      "Country": "Portugal"
  },
  {
      "id": 25,
      "Country": "Russia"
  },
  {
      "id": 26,
      "Country": "South Korea"
  },
  {
      "id": 27,
      "Country": "Sweden"
  },
  {
      "id": 28,
      "Country": "Turkey"
  },
  {
      "id": 29,
      "Country": "United States"
  },
  {
      "id": 30,
      "Country": "Vietnam"
  }
]